{
    "$schema": "https://schema.management.azure.com/schemas/2019-04-01/deploymentParameters.json#",
    "contentVersion": "1.0.0.0",
    "parameters": {
        "location": {
            "value": ""
        },
        "vm_name": {
            "value": ""
        },
        "shutdown_timezone": {
            "value": ""
        },
        "shutdown_time": {
            "value": ""
        },
        "enable_notification": {
            "value": ""
        },
        "notification_web_hook_url": {
            "value": ""
        },
        "notification_email": {
            "value": ""
        },
        "notification_minutes_before": {
            "value": ""
        },
        "notification_locale": {
            "value": ""
        }
    }
}